examples/__init__.py
examples/inspection.py
gcsopt/__init__.py
gcsopt/edges.py
gcsopt/graphs.py
gcsopt/plot_utils.py
gcsopt/programs.py
gcsopt/vertices.py
gcsopt/graph_problems/__init__.py
gcsopt/graph_problems/facility_location.py
gcsopt/graph_problems/from_ilp.py
gcsopt/graph_problems/minimum_spanning_tree.py
gcsopt/graph_problems/shortest_path.py
gcsopt/graph_problems/traveling_salesman.py
gcsopt/graph_problems/utils.py
gcsopt/graph_problems/rounding/__init__.py
gcsopt/graph_problems/rounding/shortest_path.py
gcsopt-0.1.2.dist-info/licenses/LICENSE
tests/__init__.py
tests/test_graph_problems.py
tests/test_graphs.py
tests/test_programs.py
gcsopt-0.1.2.dist-info/METADATA
gcsopt-0.1.2.dist-info/WHEEL
gcsopt-0.1.2.dist-info/top_level.txt
gcsopt-0.1.2.dist-info/RECORD
